pygradientify/__init__.py
pygradientify-1.0.3.dist-info/METADATA
pygradientify-1.0.3.dist-info/WHEEL
pygradientify-1.0.3.dist-info/top_level.txt
pygradientify-1.0.3.dist-info/RECORD
