Metadata-Version: 2.4
Name: pygradientify
Version: 1.0.3
Summary: make terminal ui's beautiful.
Author: sorrow
License: MIT
Project-URL: Homepage, https://github.com/xsorroww/pygradientify
Project-URL: Source, https://github.com/xsorroww/pygradientify
Project-URL: Issues, https://github.com/xsorroww/pygradientify/issues
Keywords: gradient,terminal,ansi,rgb,color
Requires-Python: >=3.8
